quickcoach_export/main.py
quickcoach_export/quickcoach_scrape.py
quickcoach_export-0.1.1.dist-info/licenses/LICENSE
quickcoach_export-0.1.1.dist-info/METADATA
quickcoach_export-0.1.1.dist-info/WHEEL
quickcoach_export-0.1.1.dist-info/entry_points.txt
quickcoach_export-0.1.1.dist-info/top_level.txt
quickcoach_export-0.1.1.dist-info/RECORD
