Metadata-Version: 2.4
Name: quickcoach-export
Version: 0.1.1
Summary: Export your workout history from QuickCoach to CSV files
Author: John Brock
License-Expression: MIT
Project-URL: Homepage, https://github.com/JohnHBrock/quickcoach-scraper
Project-URL: Repository, https://github.com/JohnHBrock/quickcoach-scraper
Project-URL: Issues, https://github.com/JohnHBrock/quickcoach-scraper/issues
Keywords: quickcoach
Requires-Python: >=3.13
License-File: LICENSE
Requires-Dist: selenium>=4.38.0
Dynamic: license-file
